{"2025/08/25": ["2.1.1.6", "修复了不显示更新日志的问题\n添加了更新日志显示公告"], "2025/09/05": ["2.2.0.7", "添加了清理缓存功能\n更改和添加了上方的menu栏的功能:\n  更新相关功能移动到更新菜单栏\n  添加了\"编辑/选项\"菜单栏\n修复了无法检查更新的问题", 5], "2025/10/02": ["2.2.1.8", "添加了语言选择功能\n添加了找不到文件的提示\n重构了一些代码"], "2025/10/03": ["2.2.2.9", "修复了一些bug:\n  修复了2.1.1.8的更新日志不显示版本号的问题\n  修复了在英文下,\"关于\"页面出现中文按钮的问题\n  修复了\"清理缓存\"的问题:\n    修复了\"全选\"会切换为\"部分选中\"提示的问题\n    修复了部分选中时候显示为\"全不选\"问题\n  \n对\"更换语言包需要重启\"更新:\n  修改了语言提示和显示图标\n  修改了点击步骤，不会再有选择仅保存语言和保存所有设置的提示\n  删除了\"立即重启\"按钮", 12], "2025/11/26": ["2.2.3.10", "修复了一些bug\n初始化界面自动获取语言", 2]}